{
    "Url": "www.epdata.es/variacion-anual-inflacion-ecuador/1aae33e0-8a17-4937-8f58-70ed22b61f1f",
    "Respuesta": {
        "Id": "1aae33e0-8a17-4937-8f58-70ed22b61f1f",
        "Url": "www.epdata.es/variacion-anual-inflacion-ecuador/1aae33e0-8a17-4937-8f58-70ed22b61f1f",
        "Titulo": "Variación anual de la inflación en Ecuador",
        "Subtitulo": "",
        "Datos": {
            "Metricas": [
                {
                    "Id": 0,
                    "Nombre": "Variación interanual (%)",
                    "SonDatosNumericos": true,
                    "Fuente": "Instituto Nacional de Estadística y Censos",
                    "Clasificacion": null,
                    "Unidad": "%",
                    "Escala": "Unidades",
                    "EscalaFactorPotencia10": 0,
                    "Datos": [
                        {
                            "Pais":"Ecuador","Agno": 2021,
                            "Periodo": "Octubre",
                            "Parametro": "Octubre",
                            "Valor": 1.47,
                            "Estado": null,
                            "Notas": null
                        },
                        {
                            "Pais":"Ecuador","Agno": 2021,
                            "Periodo": "Noviembre",
                            "Parametro": "Noviembre",
                            "Valor": 1.84,
                            "Estado": null,
                            "Notas": null
                        },
                        {
                            "Pais":"Ecuador","Agno": 2021,
                            "Periodo": "Diciembre",
                            "Parametro": "Diciembre",
                            "Valor": 1.94,
                            "Estado": null,
                            "Notas": null
                        },
                        {
                            "Pais":"Ecuador","Agno": 2022,
                            "Periodo": "Enero",
                            "Parametro": "2022",
                            "Valor": 2.56,
                            "Estado": null,
                            "Notas": null
                        },
                        {
                            "Pais":"Ecuador","Agno": 2022,
                            "Periodo": "Febrero",
                            "Parametro": "Febrero",
                            "Valor": 2.71,
                            "Estado": null,
                            "Notas": null
                        },
                        {
                            "Pais":"Ecuador","Agno": 2022,
                            "Periodo": "Marzo",
                            "Parametro": "Marzo",
                            "Valor": 2.64,
                            "Estado": null,
                            "Notas": null
                        },
                        {
                            "Pais":"Ecuador","Agno": 2022,
                            "Periodo": "Abril",
                            "Parametro": "Abril",
                            "Valor": 2.89,
                            "Estado": null,
                            "Notas": null
                        },
                        {
                            "Pais":"Ecuador","Agno": 2022,
                            "Periodo": "Mayo",
                            "Parametro": "Mayo",
                            "Valor": 3.38,
                            "Estado": null,
                            "Notas": null
                        },
                        {
                            "Pais":"Ecuador","Agno": 2022,
                            "Periodo": "Junio",
                            "Parametro": "Junio",
                            "Valor": 4.23,
                            "Estado": null,
                            "Notas": null
                        },
                        {
                            "Pais":"Ecuador","Agno": 2022,
                            "Periodo": "Julio",
                            "Parametro": "Julio",
                            "Valor": 3.86,
                            "Estado": null,
                            "Notas": null
                        },
                        {
                            "Pais":"Ecuador","Agno": 2022,
                            "Periodo": "Agosto",
                            "Parametro": "Agosto",
                            "Valor": 3.77,
                            "Estado": null,
                            "Notas": null
                        },
                        {
                            "Pais":"Ecuador","Agno": 2022,
                            "Periodo": "Septiembre",
                            "Parametro": "Septiembre",
                            "Valor": 4.12,
                            "Estado": null,
                            "Notas": null
                        },
                        {
                            "Pais":"Ecuador","Agno": 2022,
                            "Periodo": "Octubre",
                            "Parametro": "Octubre",
                            "Valor": 4.02,
                            "Estado": null,
                            "Notas": null
                        }
                    ]
                }
            ]
        }
    }
}